ijsongenerators/__init__.py
ijsongenerators/aliases.py
ijsongenerators-1.0.0.dist-info/METADATA
ijsongenerators-1.0.0.dist-info/WHEEL
ijsongenerators-1.0.0.dist-info/top_level.txt
ijsongenerators-1.0.0.dist-info/zip-safe
ijsongenerators-1.0.0.dist-info/RECORD
